{
    "module": "Module 3 - k-NN Re-ranking & Recommendation Engine",
    "output_for": "Final Student Interface",
    "student_context": {
        "student_id": "UET230072",
        "career_goal": "Industrial Automation Engineer",
        "career_track": "Tự động hóa công nghiệp",
        "current_semester": 3,
        "gpa": 1.3,
        "completed_credits": 28,
        "credit_limit": 14,
        "risk_level": "HIGH"
    },
    "planning_status": {
        "has_roadmap": true,
        "reason": null
    },
    "knn_metadata": {
        "k": 5,
        "neighbors_found": 5,
        "neighbors": [
            {
                "student_id": "UET230057",
                "gpa": 1.28,
                "career_goal": "Industrial Automation Engineer",
                "distance": 0.0112,
                "study_hours_per_week": 13
            },
            {
                "student_id": "UET230064",
                "gpa": 1.85,
                "career_goal": "Industrial Automation Engineer",
                "distance": 0.082,
                "study_hours_per_week": 12
            },
            {
                "student_id": "UET230033",
                "gpa": 1.88,
                "career_goal": "Industrial Automation Engineer",
                "distance": 0.1152,
                "study_hours_per_week": 14
            },
            {
                "student_id": "UET230030",
                "gpa": 1.96,
                "career_goal": "Industrial Automation Engineer",
                "distance": 0.1242,
                "study_hours_per_week": 14
            },
            {
                "student_id": "UET230043",
                "gpa": 2.17,
                "career_goal": "Industrial Automation Engineer",
                "distance": 0.1305,
                "study_hours_per_week": 10
            }
        ]
    },
    "final_output": {
        "roadmap": [
            {
                "rank": 1,
                "final_score": 0.4528,
                "score_breakdown": {
                    "career_score": 0.0,
                    "peer_score": 0.966,
                    "load_score": 1.0,
                    "foundation_score": 0.596,
                    "balance_score": 1.0
                },
                "plan_metrics": {
                    "semester_credits": [
                        13,
                        13
                    ],
                    "foundation_credits": 17,
                    "first_sem_foundation_credits": 6,
                    "overall_foundation_score": 0.654,
                    "early_foundation_score": 0.462,
                    "foundation_score": 0.596,
                    "balance_score": 1.0
                },
                "semesters": [
                    {
                        "semester_offset": 1,
                        "courses": [
                            "INT1009",
                            "POL1001",
                            "PHI1002",
                            "RBE2001",
                            "MAT1093"
                        ],
                        "total_credits": 13
                    },
                    {
                        "semester_offset": 2,
                        "courses": [
                            "INT2210",
                            "ELT3290",
                            "ELT3144",
                            "HIS1001"
                        ],
                        "total_credits": 13
                    }
                ],
                "total_credits": 26,
                "covered_skills": []
            },
            {
                "rank": 2,
                "final_score": 0.4528,
                "score_breakdown": {
                    "career_score": 0.0,
                    "peer_score": 0.966,
                    "load_score": 1.0,
                    "foundation_score": 0.596,
                    "balance_score": 1.0
                },
                "plan_metrics": {
                    "semester_credits": [
                        13,
                        13
                    ],
                    "foundation_credits": 17,
                    "first_sem_foundation_credits": 6,
                    "overall_foundation_score": 0.654,
                    "early_foundation_score": 0.462,
                    "foundation_score": 0.596,
                    "balance_score": 1.0
                },
                "semesters": [
                    {
                        "semester_offset": 1,
                        "courses": [
                            "INT1009",
                            "POL1001",
                            "PHI1002",
                            "RBE2001",
                            "MAT1093"
                        ],
                        "total_credits": 13
                    },
                    {
                        "semester_offset": 2,
                        "courses": [
                            "INT2210",
                            "ELT3295",
                            "ELT3144",
                            "HIS1001"
                        ],
                        "total_credits": 13
                    }
                ],
                "total_credits": 26,
                "covered_skills": []
            },
            {
                "rank": 3,
                "final_score": 0.4528,
                "score_breakdown": {
                    "career_score": 0.0,
                    "peer_score": 0.966,
                    "load_score": 1.0,
                    "foundation_score": 0.596,
                    "balance_score": 1.0
                },
                "plan_metrics": {
                    "semester_credits": [
                        13,
                        13
                    ],
                    "foundation_credits": 17,
                    "first_sem_foundation_credits": 6,
                    "overall_foundation_score": 0.654,
                    "early_foundation_score": 0.462,
                    "foundation_score": 0.596,
                    "balance_score": 1.0
                },
                "semesters": [
                    {
                        "semester_offset": 1,
                        "courses": [
                            "INT1009",
                            "POL1001",
                            "PHI1002",
                            "RBE2001",
                            "MAT1093"
                        ],
                        "total_credits": 13
                    },
                    {
                        "semester_offset": 2,
                        "courses": [
                            "INT2210",
                            "ELT3144",
                            "HIS1001",
                            "ELT2201"
                        ],
                        "total_credits": 13
                    }
                ],
                "total_credits": 26,
                "covered_skills": []
            }
        ],
        "skills_to_improve": [
            {
                "skill": "PLC",
                "source": "career_oriented",
                "priority": "cao"
            },
            {
                "skill": "Control",
                "source": "career_oriented",
                "priority": "cao"
            },
            {
                "skill": "SCADA",
                "source": "career_oriented",
                "priority": "cao"
            },
            {
                "skill": "Industrial Networks",
                "source": "career_oriented",
                "priority": "cao"
            },
            {
                "skill": "Power Electronics",
                "source": "career_oriented",
                "priority": "cao"
            },
            {
                "skill": "HMI",
                "source": "career_oriented",
                "priority": "cao"
            },
            {
                "skill": "Toán nền tảng",
                "source": "peer_pattern",
                "priority": "cao"
            },
            {
                "skill": "Lập trình",
                "source": "peer_pattern",
                "priority": "cao"
            },
            {
                "skill": "Điện tử - vi xử lý",
                "source": "peer_pattern",
                "priority": "thấp"
            }
        ],
        "study_hours_per_week": {
            "total_per_week": 16,
            "breakdown": {
                "ly_thuyet": 6,
                "thuc_hanh": 7,
                "project": 3
            },
            "peer_average": 12.9,
            "formula_hours": 19.5
        }
    }
}